djangoldp_community/__init__.py
djangoldp_community/admin.py
djangoldp_community/apps.py
djangoldp_community/djangoldp_urls.py
djangoldp_community/models.py
djangoldp_community/views.py
djangoldp_community/management/__init__.py
djangoldp_community/management/commands/__init__.py
djangoldp_community/management/commands/create_community.py
djangoldp_community/migrations/0001_initial.py
djangoldp_community/migrations/0002_auto_20210217_1205.py
djangoldp_community/migrations/0003_auto_20210218_1145.py
djangoldp_community/migrations/0004_auto_20210323_1121.py
djangoldp_community/migrations/0005_communityaddress_communityprofile.py
djangoldp_community/migrations/0006_auto_20210324_1113.py
djangoldp_community/migrations/0007_auto_20210324_1146.py
djangoldp_community/migrations/0008_auto_20210415_1744.py
djangoldp_community/migrations/0009_auto_20220630_0033.py
djangoldp_community/migrations/0010_auto_20220630_0034.py
djangoldp_community/migrations/0011_auto_20220711_0837.py
djangoldp_community/migrations/0012_alter_community_options_and_more.py
djangoldp_community/migrations/0013_auto_20231014_1439.py
djangoldp_community/migrations/0014_community_owner.py
djangoldp_community/migrations/0015_add_timestamps_to_models.py
djangoldp_community/migrations/__init__.py
djangoldp_community/tests/__init__.py
djangoldp_community/tests/runner.py
djangoldp_community/tests/tests_model.py
djangoldp_community/tests/tests_permissions.py
djangoldp_community-5.0.0.dist-info/METADATA
djangoldp_community-5.0.0.dist-info/WHEEL
djangoldp_community-5.0.0.dist-info/top_level.txt
djangoldp_community-5.0.0.dist-info/RECORD
