Metadata-Version: 2.4
Name: djangoldp_community
Version: 5.0.0
Summary: djangoldp package for community data models
Home-page: https://git.startinblox.com/djangoldp-packages/djangoldp-community
Author: Startin'blox
Author-email: jbaptiste@startinblox.com
License: MIT
Requires-Dist: djangoldp~=5.0.0
Requires-Dist: djangoldp-account~=5.0.0
Requires-Dist: djangoldp-i18n~=5.0.0
Requires-Dist: djangoldp-circle~=5.0.0
Requires-Dist: djangoldp-project~=6.0.0
Requires-Dist: djangoldp-joboffer~=5.0.0
Requires-Dist: djangoldp-conversation~=5.0.0
Requires-Dist: djangoldp-skill~=5.0.0
Requires-Dist: djangoldp-notification~=5.0.0
